django_ajax/__init__.py
django_ajax/media/ajax/csrf_token.min.js
django_ajax/static/ajax/csrf_token.min.js
django_ajax/templatetags/__init__.py
django_ajax/templatetags/csrf_tags.py
django_ajax_csrf-1.0.2.dist-info/DESCRIPTION.rst
django_ajax_csrf-1.0.2.dist-info/METADATA
django_ajax_csrf-1.0.2.dist-info/RECORD
django_ajax_csrf-1.0.2.dist-info/WHEEL
django_ajax_csrf-1.0.2.dist-info/metadata.json
django_ajax_csrf-1.0.2.dist-info/top_level.txt
