Metadata-Version: 2.0
Name: django-ajax-csrf
Version: 1.0.2
Summary: Django app - bundle csrf token additioner for JavaScript
Home-page: https://github.com/nnsnodnb/django-ajax-csrf
Author: nnsnodnb
Author-email: ahr63_gej@me.com
License: MIT
Keywords: django csrf staticfiles
Platform: any
Classifier: Programming Language :: Python :: 2
Classifier: Programming Language :: Python :: 2.7
Classifier: Programming Language :: Python :: 3
Classifier: Programming Language :: Python :: 3.4
Classifier: Programming Language :: Python :: 3.5
Classifier: Programming Language :: Python :: 3.6
Requires-Dist: Django (>=1.7)
